{
  "project_info": {
    "project_number": "1033622455717",
    "project_id": "uangku-ichsan",
    "storage_bucket": "uangku-ichsan.firebasestorage.app"
  },
  "client": [
    {
      "client_info": {
        "mobilesdk_app_id": "1:1033622455717:android:7227816ba5ad49dbff944c",
        "android_client_info": {
          "package_name": "com.example.uangku"
        }
      },
      "oauth_client": [],
      "api_key": [
        {
          "current_key": "AIzaSyAtlfMx1hwYVBsEsewM7QAi87fcPhnGjYs"
        }
      ],
      "services": {
        "appinvite_service": {
          "other_platform_oauth_client": []
        }
      }
    }
  ],
  "configuration_version": "1"
}